rataGUI/__init__.py
rataGUI/main.py
rataGUI/utils.py
rataGUI/cameras/BaseCamera.py
rataGUI/cameras/BaslerCamera.py
rataGUI/cameras/FLIRCamera.py
rataGUI/cameras/TemplateCamera.py
rataGUI/cameras/VideoReader.py
rataGUI/cameras/WebCamera.py
rataGUI/cameras/__init__.py
rataGUI/interface/__init__.py
rataGUI/interface/camera_widget.py
rataGUI/interface/main_window.py
rataGUI/interface/start_menu.py
rataGUI/interface/design/Ui_CameraWidget.py
rataGUI/interface/design/Ui_MainWindow.py
rataGUI/interface/design/Ui_StartMenu.py
rataGUI/interface/design/cameraWidget.ui
rataGUI/interface/design/mainWindow.ui
rataGUI/interface/design/ratagui-icon.png
rataGUI/interface/design/startMenu.ui
rataGUI/interface/design/vtab_widget.py
rataGUI/plugins/__init__.py
rataGUI/plugins/base_plugin.py
rataGUI/plugins/dlc_inference.py
rataGUI/plugins/frame_display.py
rataGUI/plugins/metadata_writer.py
rataGUI/plugins/pose_tracker.py
rataGUI/plugins/sleap_inference.py
rataGUI/plugins/template_plugin.py
rataGUI/plugins/video_writer.py
rataGUI/triggers/__init__.py
rataGUI/triggers/base_trigger.py
rataGUI/triggers/nidaqmx_counter.py
rataGUI/triggers/template_trigger.py
rataGUI/triggers/udp_socket.py
rataGUI-0.2.1.dist-info/LICENSE
rataGUI-0.2.1.dist-info/METADATA
rataGUI-0.2.1.dist-info/WHEEL
rataGUI-0.2.1.dist-info/entry_points.txt
rataGUI-0.2.1.dist-info/top_level.txt
rataGUI-0.2.1.dist-info/RECORD
