Metadata-Version: 2.1
Name: rataGUI
Version: 0.2.1
Summary: Customizable and intuitive video acquisition system for real-time animal tracking and behavior quantification
Author-email: Brian Hu <brainhu42@gmail.com>
License: LICENSE
Project-URL: Homepage, https://github.com/BrainHu42/rataGUI
Keywords: tracking,pose estimation,video,neuroscience,deep learning
Classifier: Programming Language :: Python :: 3
Classifier: Programming Language :: Python :: 3.10
Classifier: License :: OSI Approved :: GNU General Public License v2 (GPLv2)
Classifier: Operating System :: OS Independent
Requires-Python: >=3.10
License-File: LICENSE
Requires-Dist: darkdetect
Requires-Dist: numpy ==1.25.*
Requires-Dist: opencv-python-headless ==4.8.*
Requires-Dist: pillow
Requires-Dist: pyqt6
Requires-Dist: pyqtconfig
Requires-Dist: tensorflow ==2.9.* ; sys_platform != "darwin"
Requires-Dist: tensorflow ; sys_platform == "darwin"
